src/hex7seg.v
// ENGR_190 Lab 7, hex 7 segment display
// James Hicks, 02/22/23

module hex7seg(

input   [3:0] c_i,      //3 bits input
output  [0:6] disp_o);  //7 bit output
//                                     7 seg   hexI   hexO
 assign disp_o =( (c_i == 4'h0) ? 7'b1000000 : // 0 | 40
                  (c_i == 4'h1) ? 7'b1111001 : // 1 | 79
                  (c_i == 4'h2) ? 7'b0100100 : // 2 | 24
                  (c_i == 4'h3) ? 7'b0110000 : // 3 | 30
                  (c_i == 4'h4) ? 7'b0011001 : // 4 | 19
                  (c_i == 4'h5) ? 7'b0010010 : // 5 | 12
                  (c_i == 4'h6) ? 7'b0000010 : // 6 | 02
                  (c_i == 4'h7) ? 7'b1111000 : // 7 | 78
                  (c_i == 4'h8) ? 7'b0000000 : // 8 | 00
                  (c_i == 4'h9) ? 7'b0010000 : // 9 | 10
                  (c_i == 4'ha) ? 7'b0001000 :
                  (c_i == 4'hb) ? 7'b0000011 :
                  (c_i == 4'hc) ? 7'b1000110 :
                  (c_i == 4'hd) ? 7'b0100001 :
                  (c_i == 4'he) ? 7'b0000110 :
                /*(c_i == 4'hf)*/ 7'b0001110);
endmodule

src/zeroBlanker.v
// ENGR_190 James Hicks 3/16/2023

module zeroBlanker
  (
    input        useBlanker_i,
    input  [6:0] displayToBlank_i,
    output [6:0] blankedDisplay_o
  );

assign blankedDisplay_o=(useBlanker_i && (displayToBlank_i == 7'b1000000))
                             ? 7'b1111111 : displayToBlank_i;

endmodule

src/bin2bcd.v
// ENGR_190 bin2bcd James Hicks 03/07/2023

module bin2bcd
  (
    input  [6:0] bin_i,
    output [3:0] msb_o,
    output [3:0] lsb_o
  );
  assign msb_o = bin_i / 10;
  assign lsb_o = bin_i % 10;
endmodule

src/zeroHourManager.v
// ENGR_190 James Hicks 03/16/2023
// Manages the zero hour both on the input off the switches and on the
// output out of clock 1

module zeroHourManager
  #(parameter cntr_tc_p = 11)
  (
    input        manageZeroHour_i,
    input  [6:0] hrs_unmanaged_i,
    output [6:0] hrs_managed_o
  );

  assign hrs_managed_o = 
  (manageZeroHour_i && (hrs_unmanaged_i [6:0] == 7'b0)) ? cntr_tc_p + 1 :
  (manageZeroHour_i && (hrs_unmanaged_i [6:0] == cntr_tc_p + 1)) ? 7'b0 :
  hrs_unmanaged_i [6:0];

endmodule

src/cntrStage.v
// ENGR_190 example Verilog, general-purpose cascadable counter stage
// Rick Nungester 2/28/17
// Updated by James Hicks (added load function)
// 03/07/23

module cntrStage
  #(parameter cntr_tc_p = 9) (
  input                    clk_i,
  input                    nLoadNow_i,  //boolean flag to tell us to load
  input  [cntr_bits_p-1:0] load_i,      //the value we are actually loading
  input                    enable_i,
  output                   term_cnt_o,
  output [cntr_bits_p-1:0] count_o );

  localparam cntr_bits_p = $clog2(cntr_tc_p + 1);

  reg [cntr_bits_p-1:0] count_r = 0;

  always @(posedge clk_i) begin
    if (~nLoadNow_i)
      count_r <= load_i;            // if loadNow_i then count_r = load_i
    else if (enable_i) begin
      if (count_r == cntr_tc_p[cntr_bits_p-1:0])
        count_r <= 1'b0;            // enabled & at tc, wrap to 0
      else
        count_r <= count_r + 1'b1;  // enabled & not TC, so increment
    end
  end

  // set outputs from registers used in the always block
  assign count_o = count_r;
  assign term_cnt_o = (count_r == cntr_tc_p[cntr_bits_p-1:0]);

endmodule

src/clock1.v
// ENGR_190 clock1 James Hicks 03/07/2023

module clock1 
  #(parameter hrs_tc_p  = 11,
              mins_tc_p = 59,
              secs_tc_p = 59,
              clk_tc_p  = 49999999)
  (
    input        clk_i,
    input        nLoadNow_i,
    input  [6:0] loadHrs_i,
    input  [6:0] loadMins_i,
    output [6:0] hrs_o,
    output [6:0] mins_o,
    output [6:0] secs_o
  );

  wire stage1_en_w;
  wire stage2_en_w;
  wire stage3_en_w;

  cntrStage
  #(.cntr_tc_p (clk_tc_p))
  stage0
  (
    .clk_i      (clk_i),
    .nLoadNow_i (nLoadNow_i),
    .load_i     (26'b0),        // (see if this will work)
    .enable_i   (1'b1),
    .term_cnt_o (stage1_en_w),
    .count_o    ()             // no connect
  );

  cntrStage
  #(.cntr_tc_p (secs_tc_p))
  stage1
  (
    .clk_i      (clk_i),
    .nLoadNow_i (nLoadNow_i),
    .load_i     (7'b0000000), // Hard code seconds load to 0
    .enable_i   (stage1_en_w),
    .term_cnt_o (stage2_en_w),
    .count_o    (secs_o)
  );

  cntrStage
  #(.cntr_tc_p (mins_tc_p))
  stage2
  (
    .clk_i      (clk_i),
    .nLoadNow_i (nLoadNow_i),
    .load_i     (loadMins_i),
    .enable_i   (stage1_en_w && stage2_en_w),
    .term_cnt_o (stage3_en_w),
    .count_o    (mins_o)
  );

  cntrStage
  #(.cntr_tc_p (hrs_tc_p))
  stage3
  (
    .clk_i      (clk_i),
    .nLoadNow_i (nLoadNow_i),
    .load_i     (loadHrs_i),
    .enable_i   (stage1_en_w && stage2_en_w && stage3_en_w),
    .term_cnt_o (),             // no connect
    .count_o    (hrs_o)
  );

endmodule

src/bcd2bin.v
// ENGR_190 bcd2bin James Hicks 3/16/2023

module bcd2bin
  (
   input  [3:0] msb_i,
   input  [3:0] lsb_i,
   output [6:0] bin_o
  );

  wire [3:0] digit1, digit2;

  assign digit1 = (msb_i[3:0] > 9) ? 4'b0000 : msb_i[3:0];
  assign digit2 = (lsb_i[3:0] > 9) ? 4'b0000 : lsb_i[3:0];

  assign bin_o = (digit1 * 10) + digit2;

endmodule

src/clock2.v
// ENGR_190 James Hicks 03/16/2023
// Takes in binary load and outputs bcd
// Binary in bcd out

module clock2
  #(parameter    hrs_tc_p  = 11,
                 mins_tc_p = 59,
                 secs_tc_p = 59,
                 clk_tc_p  = 49999999)
  (
    input        clk_i,
    input        nLoadNow_i,
    input        manageZeroHour_i,
    input        useBlanker_i,
    input  [17:2]switch_i,
    output [6:0] hrs_msb_o,
    output [6:0] hrs_lsb_o,
    output [6:0] mins_msb_o,
    output [6:0] mins_lsb_o,
    output [6:0] secs_msb_o,
    output [6:0] secs_lsb_o 
  );

    // load input wires for clock 1
    wire   [6:0] loadHrs_w;
    wire   [6:0] loadMins_w;

    // wire used as input for the  zero hour output manager
    wire   [6:0] zeroHourOutputManager_w;

    // wire used as input for the zero hour input manager
    wire   [6:0] zeroHourInputManager_w;

    // wires used as input to clock 1
    wire   [6:0] hrs_binary_w;
    wire   [6:0] mins_binary_w;
    wire   [6:0] secs_binary_w;

    // wires used as inputs to the hex7segs
    wire   [3:0] bcd_hrs_msb_w;
    wire   [3:0] bcd_hrs_lsb_w;
    wire   [3:0] bcd_mins_msb_w;
    wire   [3:0] bcd_mins_lsb_w;
    wire   [3:0] bcd_secs_msb_w;
    wire   [3:0] bcd_secs_lsb_w;

    // wire used as the input of the blanker
    wire   [6:0] hrs_to_blanker_w;

    // Take inputs off the switches and turn them into binary
    bcd2bin hrsBcd2Bin
  (
    .msb_i         (switch_i[17:14]),
    .lsb_i         (switch_i[13:10]),
    .bin_o         (loadHrs_w)
  );

  // Take the binary output of hrsBcd2Bin and manage the zero hour
  zeroHourManager
  #(.cntr_tc_p(hrs_tc_p))
  myZeroHourInputManager
  (
    .manageZeroHour_i(manageZeroHour_i),
    .hrs_unmanaged_i (loadHrs_w),
    .hrs_managed_o   (zeroHourInputManager_w)
  );

  bcd2bin minsBcd2Bin
  (
    .msb_i         (switch_i[9:6]),
    .lsb_i         (switch_i[5:2]),
    .bin_o         (loadMins_w)
  );

  //instantiate the clock
  clock1
  #(.hrs_tc_p (hrs_tc_p),   .mins_tc_p(mins_tc_p),
    .secs_tc_p(secs_tc_p),  .clk_tc_p (clk_tc_p))
  myClock1
  (
    .clk_i        (clk_i),
    .nLoadNow_i   (nLoadNow_i),
    .loadHrs_i    (zeroHourInputManager_w),  //loadHrs_w
    .loadMins_i   (loadMins_w),
    .hrs_o        (zeroHourOutputManager_w),
    .mins_o       (mins_binary_w),
    .secs_o       (secs_binary_w)
  );

  // Manage the binary hours output for the zero hour
  zeroHourManager
  #(.cntr_tc_p(hrs_tc_p))
  myZeroHourOutputManager
  (
    .manageZeroHour_i(manageZeroHour_i),
    .hrs_unmanaged_i (zeroHourOutputManager_w),
    .hrs_managed_o   (hrs_binary_w)
  );

  // turn the binaries to bcd to be input to the hex7segs
  bin2bcd hrsBin2Bcd
  (
    .bin_i        (hrs_binary_w),
    .msb_o        (bcd_hrs_msb_w),
    .lsb_o        (bcd_hrs_lsb_w)
  );

  bin2bcd minsBin2Bcd
  (
    .bin_i        (mins_binary_w),
    .msb_o        (bcd_mins_msb_w),
    .lsb_o        (bcd_mins_lsb_w)
  );

   bin2bcd secsBin2Bcd
  (
    .bin_i        (secs_binary_w),
    .msb_o        (bcd_secs_msb_w),
    .lsb_o        (bcd_secs_lsb_w)
  );

  // Send the bcd's to the hex 7 segs
   hex7seg hrs_msb
  (
    .c_i           (bcd_hrs_msb_w),
    .disp_o        (hrs_to_blanker_w)
  );

  //send the hex7seg output for the hrs hex7seg to the zeroblanker
  zeroBlanker myZeroBlanker
  (
    .useBlanker_i    (useBlanker_i),
    .displayToBlank_i(hrs_to_blanker_w),
    .blankedDisplay_o(hrs_msb_o)
  );

    hex7seg hrs_lsb
  (
    .c_i           (bcd_hrs_lsb_w),
    .disp_o        (hrs_lsb_o)
  );

  hex7seg mins_msb
  (
    .c_i           (bcd_mins_msb_w),
    .disp_o        (mins_msb_o)
  );

  hex7seg mins_lsb
  (
    .c_i           (bcd_mins_lsb_w),
    .disp_o        (mins_lsb_o)
  );

  hex7seg secs_msb
  (
    .c_i           (bcd_secs_msb_w),
    .disp_o        (secs_msb_o)
  );

  hex7seg secs_lsb
  (
    .c_i           (bcd_secs_lsb_w),
    .disp_o        (secs_lsb_o)
  );

endmodule

sim/clock1_tb.v
// ENGR 190 clock1_tb James Hicks 03/07/2023

// This testbench works for 

`timescale 1s/10ms

module clock1_tb;
reg clk_r;
reg  nLoadNow_r;
reg  [6:0] loadHrs_r;
reg  [6:0] loadMins_r;
wire [6:0] hrs_w;
wire [6:0] mins_w;
wire [6:0] secs_w;

  always
    #0.250 clk_r = ~clk_r;

  initial begin
    $dumpfile("a.vcd");
    $dumpvars;
    $display("time  hrs  mins  secs  loadNow  hrsLoadIn  minsLoadIn");
    $monitor("%4d  %3d  %4d  %4d  %7d  %9d  %9d", $time, hrs_w, mins_w, secs_w, nLoadNow_r, loadHrs_r, loadMins_r);

            clk_r      =  1'b1;
            loadHrs_r  = 7'b0000000;
            loadMins_r = 7'b0000000;
            nLoadNow_r = 1'b0;
            #1
            nLoadNow_r = 1'b1;
            #50
            loadHrs_r  = 7'b0000111;
            loadMins_r = 7'b0000111;
            nLoadNow_r = 1'b0;
            #1
            nLoadNow_r = 1'b1;
            #1000 $finish;
  end

  clock1 
  #(.clk_tc_p (1'b1), .secs_tc_p(10), .mins_tc_p(10), .hrs_tc_p(10))
    clock1(
      .clk_i     (clk_r),
      .nLoadNow_i(nLoadNow_r),
      .loadHrs_i (loadHrs_r),
      .loadMins_i(loadMins_r),
      .hrs_o     (hrs_w),
      .mins_o    (mins_w),
      .secs_o    (secs_w)
    );

endmodule

sim/a.vcd
$date
	Sat Mar 18 20:12:54 2023
$end
$version
	Icarus Verilog
$end
$timescale
	10ms
$end
$scope module clock1_tb $end
$var wire 7 ! secs_w [6:0] $end
$var wire 7 " mins_w [6:0] $end
$var wire 7 # hrs_w [6:0] $end
$var reg 1 $ clk_r $end
$var reg 7 % loadHrs_r [6:0] $end
$var reg 7 & loadMins_r [6:0] $end
$var reg 1 ' nLoadNow_r $end
$scope module clock1 $end
$var wire 1 $ clk_i $end
$var wire 7 ( loadHrs_i [6:0] $end
$var wire 7 ) loadMins_i [6:0] $end
$var wire 1 ' nLoadNow_i $end
$var wire 1 * stage3_en_w $end
$var wire 1 + stage2_en_w $end
$var wire 1 , stage1_en_w $end
$var wire 7 - secs_o [6:0] $end
$var wire 7 . mins_o [6:0] $end
$var wire 7 / hrs_o [6:0] $end
$var parameter 1 0 clk_tc_p $end
$var parameter 32 1 hrs_tc_p $end
$var parameter 32 2 mins_tc_p $end
$var parameter 32 3 secs_tc_p $end
$scope module stage0 $end
$var wire 1 $ clk_i $end
$var wire 1 4 count_o $end
$var wire 1 5 enable_i $end
$var wire 1 6 load_i $end
$var wire 1 ' nLoadNow_i $end
$var wire 1 , term_cnt_o $end
$var parameter 32 7 cntr_bits_p $end
$var parameter 1 8 cntr_tc_p $end
$var reg 1 9 count_r $end
$upscope $end
$scope module stage1 $end
$var wire 1 $ clk_i $end
$var wire 4 : count_o [3:0] $end
$var wire 1 , enable_i $end
$var wire 4 ; load_i [3:0] $end
$var wire 1 ' nLoadNow_i $end
$var wire 1 + term_cnt_o $end
$var parameter 32 < cntr_bits_p $end
$var parameter 32 = cntr_tc_p $end
$var reg 4 > count_r [3:0] $end
$upscope $end
$scope module stage2 $end
$var wire 1 $ clk_i $end
$var wire 4 ? count_o [3:0] $end
$var wire 1 @ enable_i $end
$var wire 4 A load_i [3:0] $end
$var wire 1 ' nLoadNow_i $end
$var wire 1 * term_cnt_o $end
$var parameter 32 B cntr_bits_p $end
$var parameter 32 C cntr_tc_p $end
$var reg 4 D count_r [3:0] $end
$upscope $end
$scope module stage3 $end
$var wire 1 $ clk_i $end
$var wire 4 E count_o [3:0] $end
$var wire 1 F enable_i $end
$var wire 4 G load_i [3:0] $end
$var wire 1 ' nLoadNow_i $end
$var wire 1 H term_cnt_o $end
$var parameter 32 I cntr_bits_p $end
$var parameter 32 J cntr_tc_p $end
$var reg 4 K count_r [3:0] $end
$upscope $end
$upscope $end
$upscope $end
$scope module clock2 $end
$var wire 1 L clk_i $end
$var wire 1 M manageZeroHour_i $end
$var wire 1 N nLoadNow_i $end
$var wire 16 O switch_i [17:2] $end
$var wire 1 P useBlanker_i $end
$var wire 7 Q zeroHourOutputManager_w [6:0] $end
$var wire 7 R zeroHourInputManager_w [6:0] $end
$var wire 7 S secs_msb_o [6:0] $end
$var wire 7 T secs_lsb_o [6:0] $end
$var wire 7 U secs_binary_w [6:0] $end
$var wire 7 V mins_msb_o [6:0] $end
$var wire 7 W mins_lsb_o [6:0] $end
$var wire 7 X mins_binary_w [6:0] $end
$var wire 7 Y loadMins_w [6:0] $end
$var wire 7 Z loadHrs_w [6:0] $end
$var wire 7 [ hrs_to_blanker_w [6:0] $end
$var wire 7 \ hrs_msb_o [6:0] $end
$var wire 7 ] hrs_lsb_o [6:0] $end
$var wire 7 ^ hrs_binary_w [6:0] $end
$var wire 4 _ bcd_secs_msb_w [3:0] $end
$var wire 4 ` bcd_secs_lsb_w [3:0] $end
$var wire 4 a bcd_mins_msb_w [3:0] $end
$var wire 4 b bcd_mins_lsb_w [3:0] $end
$var wire 4 c bcd_hrs_msb_w [3:0] $end
$var wire 4 d bcd_hrs_lsb_w [3:0] $end
$var parameter 32 e clk_tc_p $end
$var parameter 32 f hrs_tc_p $end
$var parameter 32 g mins_tc_p $end
$var parameter 32 h secs_tc_p $end
$scope module hrsBcd2Bin $end
$var wire 4 i lsb_i [3:0] $end
$var wire 4 j msb_i [3:0] $end
$var wire 4 k digit2 [3:0] $end
$var wire 4 l digit1 [3:0] $end
$var wire 7 m bin_o [6:0] $end
$upscope $end
$scope module hrsBin2Bcd $end
$var wire 4 n msb_o [3:0] $end
$var wire 4 o lsb_o [3:0] $end
$var wire 7 p bin_i [6:0] $end
$upscope $end
$scope module hrs_lsb $end
$var wire 4 q c_i [3:0] $end
$var wire 7 r disp_o [0:6] $end
$upscope $end
$scope module hrs_msb $end
$var wire 4 s c_i [3:0] $end
$var wire 7 t disp_o [0:6] $end
$upscope $end
$scope module minsBcd2Bin $end
$var wire 4 u lsb_i [3:0] $end
$var wire 4 v msb_i [3:0] $end
$var wire 4 w digit2 [3:0] $end
$var wire 4 x digit1 [3:0] $end
$var wire 7 y bin_o [6:0] $end
$upscope $end
$scope module minsBin2Bcd $end
$var wire 4 z msb_o [3:0] $end
$var wire 4 { lsb_o [3:0] $end
$var wire 7 | bin_i [6:0] $end
$upscope $end
$scope module mins_lsb $end
$var wire 4 } c_i [3:0] $end
$var wire 7 ~ disp_o [0:6] $end
$upscope $end
$scope module mins_msb $end
$var wire 4 !" c_i [3:0] $end
$var wire 7 "" disp_o [0:6] $end
$upscope $end
$scope module myClock1 $end
$var wire 1 L clk_i $end
$var wire 7 #" loadMins_i [6:0] $end
$var wire 1 N nLoadNow_i $end
$var wire 1 $" stage3_en_w $end
$var wire 1 %" stage2_en_w $end
$var wire 1 &" stage1_en_w $end
$var wire 7 '" secs_o [6:0] $end
$var wire 7 (" mins_o [6:0] $end
$var wire 7 )" loadHrs_i [6:0] $end
$var wire 7 *" hrs_o [6:0] $end
$var parameter 32 +" clk_tc_p $end
$var parameter 32 ," hrs_tc_p $end
$var parameter 32 -" mins_tc_p $end
$var parameter 32 ." secs_tc_p $end
$scope module stage0 $end
$var wire 1 L clk_i $end
$var wire 26 /" count_o [25:0] $end
$var wire 1 0" enable_i $end
$var wire 26 1" load_i [25:0] $end
$var wire 1 N nLoadNow_i $end
$var wire 1 &" term_cnt_o $end
$var parameter 32 2" cntr_bits_p $end
$var parameter 32 3" cntr_tc_p $end
$var reg 26 4" count_r [25:0] $end
$upscope $end
$scope module stage1 $end
$var wire 1 L clk_i $end
$var wire 6 5" count_o [5:0] $end
$var wire 1 &" enable_i $end
$var wire 6 6" load_i [5:0] $end
$var wire 1 N nLoadNow_i $end
$var wire 1 %" term_cnt_o $end
$var parameter 32 7" cntr_bits_p $end
$var parameter 32 8" cntr_tc_p $end
$var reg 6 9" count_r [5:0] $end
$upscope $end
$scope module stage2 $end
$var wire 1 L clk_i $end
$var wire 6 :" count_o [5:0] $end
$var wire 1 ;" enable_i $end
$var wire 6 <" load_i [5:0] $end
$var wire 1 N nLoadNow_i $end
$var wire 1 $" term_cnt_o $end
$var parameter 32 =" cntr_bits_p $end
$var parameter 32 >" cntr_tc_p $end
$var reg 6 ?" count_r [5:0] $end
$upscope $end
$scope module stage3 $end
$var wire 1 L clk_i $end
$var wire 4 @" count_o [3:0] $end
$var wire 1 A" enable_i $end
$var wire 4 B" load_i [3:0] $end
$var wire 1 N nLoadNow_i $end
$var wire 1 C" term_cnt_o $end
$var parameter 32 D" cntr_bits_p $end
$var parameter 32 E" cntr_tc_p $end
$var reg 4 F" count_r [3:0] $end
$upscope $end
$upscope $end
$scope module myZeroBlanker $end
$var wire 7 G" displayToBlank_i [6:0] $end
$var wire 1 P useBlanker_i $end
$var wire 7 H" blankedDisplay_o [6:0] $end
$upscope $end
$scope module myZeroHourInputManager $end
$var wire 7 I" hrs_unmanaged_i [6:0] $end
$var wire 1 M manageZeroHour_i $end
$var wire 7 J" hrs_managed_o [6:0] $end
$var parameter 32 K" cntr_tc_p $end
$upscope $end
$scope module myZeroHourOutputManager $end
$var wire 7 L" hrs_unmanaged_i [6:0] $end
$var wire 1 M manageZeroHour_i $end
$var wire 7 M" hrs_managed_o [6:0] $end
$var parameter 32 N" cntr_tc_p $end
$upscope $end
$scope module secsBin2Bcd $end
$var wire 7 O" bin_i [6:0] $end
$var wire 4 P" msb_o [3:0] $end
$var wire 4 Q" lsb_o [3:0] $end
$upscope $end
$scope module secs_lsb $end
$var wire 4 R" c_i [3:0] $end
$var wire 7 S" disp_o [0:6] $end
$upscope $end
$scope module secs_msb $end
$var wire 4 T" c_i [3:0] $end
$var wire 7 U" disp_o [0:6] $end
$upscope $end
$upscope $end
$enddefinitions $end
$comment Show the parameter values. $end
$dumpall
b1011 N"
b1011 K"
b1011 E"
b100 D"
b111011 >"
b110 ="
b111011 8"
b110 7"
b10111110101111000001111111 3"
b11010 2"
b111011 ."
b111011 -"
b1011 ,"
b10111110101111000001111111 +"
b111011 h
b111011 g
b1011 f
b10111110101111000001111111 e
b1010 J
b100 I
b1010 C
b100 B
b1010 =
b100 <
18
b1 7
b1010 3
b1010 2
b1010 1
10
$end
#0
$dumpvars
b1000000 U"
b0 T"
b1000000 S"
b0 R"
b0 Q"
b0 P"
b0 O"
b0xx00 M"
b0 L"
bx J"
bx I"
bx H"
bx G"
b0 F"
0C"
bx B"
0A"
b0 @"
b0 ?"
bx <"
0;"
b0 :"
b0 9"
b0 6"
b0 5"
b0 4"
b0 1"
10"
b0 /"
b0 *"
bx )"
b0 ("
b0 '"
0&"
0%"
0$"
bx #"
b1000000 ""
b0 !"
b1000000 ~
b0 }
b0 |
b0 {
b0 z
bx y
bx x
bx w
bz v
bz u
bx t
bx s
bx r
bx q
b0xx00 p
bx o
bx n
bx m
bx l
bx k
bz j
bz i
bx d
bx c
b0 b
b0 a
b0 `
b0 _
b0xx00 ^
bx ]
bx \
bx [
bx Z
bx Y
b0 X
b1000000 W
b1000000 V
b0 U
b1000000 T
b1000000 S
bx R
b0 Q
zP
bz O
zN
zM
zL
bx K
xH
b0 G
0F
bx E
bx D
b0 A
0@
bx ?
b0 >
b0 ;
b0 :
09
06
15
04
b0xxxx /
b0xxxx .
b0 -
0,
0+
x*
b0 )
b0 (
0'
b0 &
b0 %
1$
b0xxxx #
b0xxxx "
b0 !
$end
#25
0$
#50
0H
b0 #
b0 /
b0 E
b0 K
0*
b0 "
b0 .
b0 ?
b0 D
1$
#75
0$
#100
1,
14
19
1$
1'
#125
0$
#150
0,
b1 !
b1 -
b1 :
b1 >
04
09
1$
#175
0$
#200
1,
14
19
1$
#225
0$
#250
0,
b10 !
b10 -
b10 :
b10 >
04
09
1$
#275
0$
#300
1,
14
19
1$
#325
0$
#350
0,
b11 !
b11 -
b11 :
b11 >
04
09
1$
#375
0$
#400
1,
14
19
1$
#425
0$
#450
0,
b100 !
b100 -
b100 :
b100 >
04
09
1$
#475
0$
#500
1,
14
19
1$
#525
0$
#550
0,
b101 !
b101 -
b101 :
b101 >
04
09
1$
#575
0$
#600
1,
14
19
1$
#625
0$
#650
0,
b110 !
b110 -
b110 :
b110 >
04
09
1$
#675
0$
#700
1,
14
19
1$
#725
0$
#750
0,
b111 !
b111 -
b111 :
b111 >
04
09
1$
#775
0$
#800
1,
14
19
1$
#825
0$
#850
0,
b1000 !
b1000 -
b1000 :
b1000 >
04
09
1$
#875
0$
#900
1,
14
19
1$
#925
0$
#950
0,
b1001 !
b1001 -
b1001 :
b1001 >
04
09
1$
#975
0$
#1000
1,
14
19
1$
#1025
0$
#1050
0,
1+
b1010 !
b1010 -
b1010 :
b1010 >
04
09
1$
#1075
0$
#1100
1@
1,
14
19
1$
#1125
0$
#1150
0@
0,
b1 "
b1 .
b1 ?
b1 D
0+
b0 !
b0 -
b0 :
b0 >
04
09
1$
#1175
0$
#1200
1,
14
19
1$
#1225
0$
#1250
0,
b1 !
b1 -
b1 :
b1 >
04
09
1$
#1275
0$
#1300
1,
14
19
1$
#1325
0$
#1350
0,
b10 !
b10 -
b10 :
b10 >
04
09
1$
#1375
0$
#1400
1,
14
19
1$
#1425
0$
#1450
0,
b11 !
b11 -
b11 :
b11 >
04
09
1$
#1475
0$
#1500
1,
14
19
1$
#1525
0$
#1550
0,
b100 !
b100 -
b100 :
b100 >
04
09
1$
#1575
0$
#1600
1,
14
19
1$
#1625
0$
#1650
0,
b101 !
b101 -
b101 :
b101 >
04
09
1$
#1675
0$
#1700
1,
14
19
1$
#1725
0$
#1750
0,
b110 !
b110 -
b110 :
b110 >
04
09
1$
#1775
0$
#1800
1,
14
19
1$
#1825
0$
#1850
0,
b111 !
b111 -
b111 :
b111 >
04
09
1$
#1875
0$
#1900
1,
14
19
1$
#1925
0$
#1950
0,
b1000 !
b1000 -
b1000 :
b1000 >
04
09
1$
#1975
0$
#2000
1,
14
19
1$
#2025
0$
#2050
0,
b1001 !
b1001 -
b1001 :
b1001 >
04
09
1$
#2075
0$
#2100
1,
14
19
1$
#2125
0$
#2150
0,
1+
b1010 !
b1010 -
b1010 :
b1010 >
04
09
1$
#2175
0$
#2200
1@
1,
14
19
1$
#2225
0$
#2250
0@
0,
b10 "
b10 .
b10 ?
b10 D
0+
b0 !
b0 -
b0 :
b0 >
04
09
1$
#2275
0$
#2300
1,
14
19
1$
#2325
0$
#2350
0,
b1 !
b1 -
b1 :
b1 >
04
09
1$
#2375
0$
#2400
1,
14
19
1$
#2425
0$
#2450
0,
b10 !
b10 -
b10 :
b10 >
04
09
1$
#2475
0$
#2500
1,
14
19
1$
#2525
0$
#2550
0,
b11 !
b11 -
b11 :
b11 >
04
09
1$
#2575
0$
#2600
1,
14
19
1$
#2625
0$
#2650
0,
b100 !
b100 -
b100 :
b100 >
04
09
1$
#2675
0$
#2700
1,
14
19
1$
#2725
0$
#2750
0,
b101 !
b101 -
b101 :
b101 >
04
09
1$
#2775
0$
#2800
1,
14
19
1$
#2825
0$
#2850
0,
b110 !
b110 -
b110 :
b110 >
04
09
1$
#2875
0$
#2900
1,
14
19
1$
#2925
0$
#2950
0,
b111 !
b111 -
b111 :
b111 >
04
09
1$
#2975
0$
#3000
1,
14
19
1$
#3025
0$
#3050
0,
b1000 !
b1000 -
b1000 :
b1000 >
04
09
1$
#3075
0$
#3100
1,
14
19
1$
#3125
0$
#3150
0,
b1001 !
b1001 -
b1001 :
b1001 >
04
09
1$
#3175
0$
#3200
1,
14
19
1$
#3225
0$
#3250
0,
1+
b1010 !
b1010 -
b1010 :
b1010 >
04
09
1$
#3275
0$
#3300
1@
1,
14
19
1$
#3325
0$
#3350
0@
0,
b11 "
b11 .
b11 ?
b11 D
0+
b0 !
b0 -
b0 :
b0 >
04
09
1$
#3375
0$
#3400
1,
14
19
1$
#3425
0$
#3450
0,
b1 !
b1 -
b1 :
b1 >
04
09
1$
#3475
0$
#3500
1,
14
19
1$
#3525
0$
#3550
0,
b10 !
b10 -
b10 :
b10 >
04
09
1$
#3575
0$
#3600
1,
14
19
1$
#3625
0$
#3650
0,
b11 !
b11 -
b11 :
b11 >
04
09
1$
#3675
0$
#3700
1,
14
19
1$
#3725
0$
#3750
0,
b100 !
b100 -
b100 :
b100 >
04
09
1$
#3775
0$
#3800
1,
14
19
1$
#3825
0$
#3850
0,
b101 !
b101 -
b101 :
b101 >
04
09
1$
#3875
0$
#3900
1,
14
19
1$
#3925
0$
#3950
0,
b110 !
b110 -
b110 :
b110 >
04
09
1$
#3975
0$
#4000
1,
14
19
1$
#4025
0$
#4050
0,
b111 !
b111 -
b111 :
b111 >
04
09
1$
#4075
0$
#4100
1,
14
19
1$
#4125
0$
#4150
0,
b1000 !
b1000 -
b1000 :
b1000 >
04
09
1$
#4175
0$
#4200
1,
14
19
1$
#4225
0$
#4250
0,
b1001 !
b1001 -
b1001 :
b1001 >
04
09
1$
#4275
0$
#4300
1,
14
19
1$
#4325
0$
#4350
0,
1+
b1010 !
b1010 -
b1010 :
b1010 >
04
09
1$
#4375
0$
#4400
1@
1,
14
19
1$
#4425
0$
#4450
0@
0,
b100 "
b100 .
b100 ?
b100 D
0+
b0 !
b0 -
b0 :
b0 >
04
09
1$
#4475
0$
#4500
1,
14
19
1$
#4525
0$
#4550
0,
b1 !
b1 -
b1 :
b1 >
04
09
1$
#4575
0$
#4600
1,
14
19
1$
#4625
0$
#4650
0,
b10 !
b10 -
b10 :
b10 >
04
09
1$
#4675
0$
#4700
1,
14
19
1$
#4725
0$
#4750
0,
b11 !
b11 -
b11 :
b11 >
04
09
1$
#4775
0$
#4800
1,
14
19
1$
#4825
0$
#4850
0,
b100 !
b100 -
b100 :
b100 >
04
09
1$
#4875
0$
#4900
1,
14
19
1$
#4925
0$
#4950
0,
b101 !
b101 -
b101 :
b101 >
04
09
1$
#4975
0$
#5000
1,
14
19
1$
#5025
0$
#5050
0,
b110 !
b110 -
b110 :
b110 >
04
09
1$
#5075
0$
#5100
b0 !
b0 -
b0 :
b0 >
b111 "
b111 .
b111 ?
b111 D
b111 #
b111 /
b111 E
b111 K
b111 A
b111 G
1$
0'
b111 &
b111 )
b111 %
b111 (
#5125
0$
#5150
1$
#5175
0$
#5200
1,
14
19
1$
1'
#5225
0$
#5250
0,
b1 !
b1 -
b1 :
b1 >
04
09
1$
#5275
0$
#5300
1,
14
19
1$
#5325
0$
#5350
0,
b10 !
b10 -
b10 :
b10 >
04
09
1$
#5375
0$
#5400
1,
14
19
1$
#5425
0$
#5450
0,
b11 !
b11 -
b11 :
b11 >
04
09
1$
#5475
0$
#5500
1,
14
19
1$
#5525
0$
#5550
0,
b100 !
b100 -
b100 :
b100 >
04
09
1$
#5575
0$
#5600
1,
14
19
1$
#5625
0$
#5650
0,
b101 !
b101 -
b101 :
b101 >
04
09
1$
#5675
0$
#5700
1,
14
19
1$
#5725
0$
#5750
0,
b110 !
b110 -
b110 :
b110 >
04
09
1$
#5775
0$
#5800
1,
14
19
1$
#5825
0$
#5850
0,
b111 !
b111 -
b111 :
b111 >
04
09
1$
#5875
0$
#5900
1,
14
19
1$
#5925
0$
#5950
0,
b1000 !
b1000 -
b1000 :
b1000 >
04
09
1$
#5975
0$
#6000
1,
14
19
1$
#6025
0$
#6050
0,
b1001 !
b1001 -
b1001 :
b1001 >
04
09
1$
#6075
0$
#6100
1,
14
19
1$
#6125
0$
#6150
0,
1+
b1010 !
b1010 -
b1010 :
b1010 >
04
09
1$
#6175
0$
#6200
1@
1,
14
19
1$
#6225
0$
#6250
0@
0,
b1000 "
b1000 .
b1000 ?
b1000 D
0+
b0 !
b0 -
b0 :
b0 >
04
09
1$
#6275
0$
#6300
1,
14
19
1$
#6325
0$
#6350
0,
b1 !
b1 -
b1 :
b1 >
04
09
1$
#6375
0$
#6400
1,
14
19
1$
#6425
0$
#6450
0,
b10 !
b10 -
b10 :
b10 >
04
09
1$
#6475
0$
#6500
1,
14
19
1$
#6525
0$
